audiopod/__init__.py
audiopod/client.py
audiopod/exceptions.py
audiopod/resources/__init__.py
audiopod/resources/denoiser.py
audiopod/resources/music.py
audiopod/resources/speaker.py
audiopod/resources/stems.py
audiopod/resources/transcription.py
audiopod/resources/voice.py
audiopod/resources/wallet.py
audiopod-2.1.0.dist-info/licenses/LICENSE
audiopod-2.1.0.dist-info/METADATA
audiopod-2.1.0.dist-info/WHEEL
audiopod-2.1.0.dist-info/top_level.txt
audiopod-2.1.0.dist-info/RECORD
