Metadata-Version: 2.4
Name: audiopod
Version: 2.1.0
Summary: Official AudioPod SDK for Python - Professional Audio Processing powered by AI
Author-email: AudioPod AI <support@audiopod.ai>
License: MIT
Project-URL: Homepage, https://audiopod.ai
Project-URL: Documentation, https://docs.audiopod.ai
Project-URL: Repository, https://github.com/AudiopodAI/audiopod-sdk-python
Project-URL: Issues, https://github.com/AudiopodAI/audiopod-sdk-python/issues
Keywords: audiopod,audio,ai,speech-to-text,transcription,text-to-speech,tts,voice-cloning,music-generation,stem-separation,denoiser,speaker-diarization
Classifier: Development Status :: 5 - Production/Stable
Classifier: Intended Audience :: Developers
Classifier: License :: OSI Approved :: MIT License
Classifier: Operating System :: OS Independent
Classifier: Programming Language :: Python :: 3
Classifier: Programming Language :: Python :: 3.8
Classifier: Programming Language :: Python :: 3.9
Classifier: Programming Language :: Python :: 3.10
Classifier: Programming Language :: Python :: 3.11
Classifier: Programming Language :: Python :: 3.12
Classifier: Topic :: Multimedia :: Sound/Audio
Classifier: Topic :: Multimedia :: Sound/Audio :: Analysis
Classifier: Topic :: Multimedia :: Sound/Audio :: Speech
Classifier: Topic :: Scientific/Engineering :: Artificial Intelligence
Classifier: Typing :: Typed
Requires-Python: >=3.8
License-File: LICENSE
Requires-Dist: requests>=2.28.0
Requires-Dist: urllib3>=1.26.0
Provides-Extra: dev
Requires-Dist: pytest>=7.0.0; extra == "dev"
Requires-Dist: pytest-cov>=4.0.0; extra == "dev"
Requires-Dist: black>=23.0.0; extra == "dev"
Requires-Dist: isort>=5.12.0; extra == "dev"
Requires-Dist: mypy>=1.0.0; extra == "dev"
Requires-Dist: types-requests>=2.28.0; extra == "dev"
Dynamic: license-file
